{
    "id": "charging_status",
    "title": {
        "en": "Charging Status !{{is|is not}} ..."
    },
    "titleFormatted": {
        "en": "Charging Status !{{is|is not}} '[[charging_state]]'"
    },
    "hint": {
        "en": "Checks if the car is inside/outside a geofence location."
    },
    "args": [
        {
            "type": "dropdown",
            "name": "charging_state",
            "title": {
                "en": "Charging status"
            },
            "values": [
                {
                    "id": "DEFAULT",
                    "title": {
                        "en": "Default"
                    }
                },
                {
                    "id": "CHARGING",
                    "title": {
                        "en": "Charging"
                    }
                },
                {
                    "id": "ERROR",
                    "title": {
                        "en": "Error"
                    }
                },
                {
                    "id": "COMPLETE",
                    "title": {
                        "en": "Complete"
                    }
                },
                {
                    "id": "FULLY_CHARGED",
                    "title": {
                        "en": "Fully Charged"
                    }
                },
                {
                    "id": "FINISHED_FULLY_CHARGED",
                    "title": {
                        "en": "Finished Fully Charged"
                    }
                },
                {
                    "id": "FINISHED_NOT_FULL",
                    "title": {
                        "en": "Finished Not Full"
                    }
                },
                {
                    "id": "INVALID",
                    "title": {
                        "en": "Invalid"
                    }
                },
                {
                    "id": "NOT_CHARGING",
                    "title": {
                        "en": "Not Charging"
                    }
                },
                {
                    "id": "PLUGGED_IN",
                    "title": {
                        "en": "Plugged In"
                    }
                },
                {
                    "id": "WAITING_FOR_CHARGING",
                    "title": {
                        "en": "Waiting For Charging"
                    }
                },
                {
                    "id": "TARGET_REACHED",
                    "title": {
                        "en": "Target Reached"
                    }
                },
                {
                    "id": "UNKNOWN",
                    "title": {
                        "en": "Unknown"
                    }
                }
            ]
        }
    ]
}